{
  "currentDay": "16",
  "maintenance": false,
  "latest": {
    "name": "Tokyo Revengers",
    "cat": "anime",
    "date": "15/04/2021 à 20:00"
  },
  "stats": {
    "poids": 8,
    "fichiers": 42680
  },
  "awaitVerification": [],
  "seasonals": [
    {
      "name": "One Piece",
      "season": false,
      "lien": "https://mega.nz/folder/Ga4FUYzB#aa0BunQ7KaHo-ZFdBmOrPg",
      "image": "https://vignette.wikia.nocookie.net/onepiece/images/d/d8/Arc_Wano.png/revision/latest?cb=20190615102959&path-prefix=fr",
      "airing": {
        "day": "Dimanche",
        "hour": "2h30"
      }
    },
    {
      "name": "Boruto",
      "season": false,
      "lien": "https://mega.nz/folder/7yhlzDjL#HCBpxmmvDcGdkPmJeEyOqQ",
      "image": "https://cdn.discordapp.com/attachments/543552811489558529/729311826965430282/IMG_20200705_142348.jpg",
      "airing": {
        "day": "Dimanche",
        "hour": "10h30"
      }
    },
    {
      "name": "Black Clover",
      "season": false,
      "lien": "https://mega.nz/folder/H7Ag3YTR#hheKvrbIJpZBgdkAX1VW_Q",
      "image": "https://media.senscritique.com/media/000017691998/source_big/Black_Clover.jpg",
      "airing": {
        "day": "Mardi",
        "hour": "11h30"
      }
    },
    {
      "name": "My Hero Academia",
      "season": "5",
      "lien": "https://mega.nz/folder/Tr5Q0AxK#86wdP1_iOfls2RF-T0JTgQ",
      "image": "https://s4.anilist.co/file/anilistcdn/media/anime/cover/large/bx117193-yZUKig9K220H.jpg",
      "airing": {
        "day": "Samedi",
        "hour": "10h00"
      }
    }
  ]
}